okin_gui/__init__.py
okin_gui/okin_gui_run.py
okin_gui/gui_files/__init__.py
okin_gui/gui_files/tab_calibration.py
okin_gui/gui_files/tab_fitting.py
okin_gui/gui_files/tab_kopt.py
okin_gui/gui_files/tab_mb_solver.py
okin_gui/gui_files/tab_modern_kinetic.py
okin_gui/gui_files/tab_outlier.py
okin_gui/gui_files/tab_rate_eq.py
okin_gui/gui_files/tab_sim.py
okin_gui/gui_files/tab_viewer.py
okin_gui/gui_files/wgt_conc.py
okin_gui/gui_files/wgt_df.py
okin_gui/gui_files/wgt_image.py
okin_gui/gui_files/wgt_qtext_window.py
okin_gui/gui_files/wgt_reactions.py
okin_gui/gui_files/wgt_save.py
okin_gui/gui_files/wgt_sb_string.py
okin_gui/gui_files/wgt_table.py
okin_gui/gui_files/window_calibration.py
okin_gui/gui_files/window_data.py
okin_gui/gui_files/window_kinetic.py
okin_gui/gui_files/window_math.py
okin_gui/gui_files/window_modeling.py
okin_gui/gui_files/window_sim.py
okin_gui/media/__init__.py
okin_gui/temp/__init__.py
okin_gui/utils/__init__.py
okin_gui/utils/convert_to_df.py
okin_gui/utils/custom_r2.py
okin_gui/utils/storage_paths.py
okin_gui/utils/style_utils.py
okin_gui-0.0.3.dist-info/licenses/LICENSE
okin_gui-0.0.3.dist-info/METADATA
okin_gui-0.0.3.dist-info/WHEEL
okin_gui-0.0.3.dist-info/top_level.txt
okin_gui-0.0.3.dist-info/RECORD
