Metadata-Version: 2.4
Name: okin_gui
Version: 0.0.3
Summary: GUI for common kinetic tests and learning basics of Kinetics in Organic chemistry.
Author: Finn
License: MIT
Project-URL: Source, https://gitlab.com/heingroup/okin_gui
Classifier: Programming Language :: Python :: 3
Classifier: License :: OSI Approved :: MIT License
Requires-Python: >=3.9
License-File: LICENSE
Requires-Dist: matplotlib
Requires-Dist: pyside6==6.7.1
Requires-Dist: scikit-learn
Requires-Dist: okin
Dynamic: license-file
